qndex/__init__.py
qndex/classify.py
qndex/classify_test.py
qndex/nlp/__init__.py
qndex/nlp/nlp.py
qndex/nlp/nlp_test.py
qndex/nlp/sentiment_analysis.py
qndex/nlp/sentiment_analysis_test.py
tensorflow_qndex-0.0.22.dist-info/DESCRIPTION.rst
tensorflow_qndex-0.0.22.dist-info/METADATA
tensorflow_qndex-0.0.22.dist-info/RECORD
tensorflow_qndex-0.0.22.dist-info/WHEEL
tensorflow_qndex-0.0.22.dist-info/metadata.json
tensorflow_qndex-0.0.22.dist-info/top_level.txt
