Metadata-Version: 2.0
Name: tensorflow-qndex
Version: 0.0.22
Summary: tensorflow-qnd x tensorflow-extenteten
Home-page: https://github.com/raviqqe/tensorflow-qndex/
Author: Yota Toyama
Author-email: raviqqe@gmail.com
License: Public Domain
Platform: UNKNOWN
Classifier: Development Status :: 3 - Alpha
Classifier: Intended Audience :: Developers
Classifier: License :: Public Domain
Classifier: Programming Language :: Python :: 3.5
Classifier: Topic :: Scientific/Engineering :: Artificial Intelligence
Classifier: Topic :: System :: Networking
Requires-Dist: argtyp
Requires-Dist: listpad
Requires-Dist: tensorflow-extenteten
Requires-Dist: tensorflow-qnd
